amsdal_glue_core/__about__.py
amsdal_glue_core/__init__.py
amsdal_glue_core/containers.py
amsdal_glue_core/py.typed
amsdal_glue_core/commands/__init__.py
amsdal_glue_core/commands/lock_command_node.py
amsdal_glue_core/commands/mutation_nodes.py
amsdal_glue_core/commands/transaction_node.py
amsdal_glue_core/commands/executors/__init__.py
amsdal_glue_core/commands/executors/data_command_executor.py
amsdal_glue_core/commands/executors/lock_command_executor.py
amsdal_glue_core/commands/executors/schema_command_executor.py
amsdal_glue_core/commands/executors/transaction_command_executor.py
amsdal_glue_core/commands/planner/__init__.py
amsdal_glue_core/commands/planner/data_command_planner.py
amsdal_glue_core/commands/planner/lock_command_planner.py
amsdal_glue_core/commands/planner/schema_command_planner.py
amsdal_glue_core/commands/planner/transaction_command_planner.py
amsdal_glue_core/common/__init__.py
amsdal_glue_core/common/enums.py
amsdal_glue_core/common/data_models/__init__.py
amsdal_glue_core/common/data_models/aggregation.py
amsdal_glue_core/common/data_models/annotation.py
amsdal_glue_core/common/data_models/conditions.py
amsdal_glue_core/common/data_models/constraints.py
amsdal_glue_core/common/data_models/data.py
amsdal_glue_core/common/data_models/field_reference.py
amsdal_glue_core/common/data_models/group_by.py
amsdal_glue_core/common/data_models/indexes.py
amsdal_glue_core/common/data_models/join.py
amsdal_glue_core/common/data_models/limit.py
amsdal_glue_core/common/data_models/order_by.py
amsdal_glue_core/common/data_models/output_type.py
amsdal_glue_core/common/data_models/query.py
amsdal_glue_core/common/data_models/schema.py
amsdal_glue_core/common/data_models/sub_query.py
amsdal_glue_core/common/data_models/vector.py
amsdal_glue_core/common/data_models/results/__init__.py
amsdal_glue_core/common/data_models/results/base.py
amsdal_glue_core/common/data_models/results/data.py
amsdal_glue_core/common/data_models/results/schema.py
amsdal_glue_core-0.1.8.dist-info/METADATA
amsdal_glue_core-0.1.8.dist-info/WHEEL
amsdal_glue_core-0.1.8.dist-info/licenses/LICENSE.txt
amsdal_glue_core-0.1.8.dist-info/licenses/NOTICE.txt
amsdal_glue_core-0.1.8.dist-info/RECORD
