Metadata-Version: 2.4
Name: amsdal-glue-core
Version: 0.1.8
Summary: AMSDAL Glue is a Python interface providing high-level abstraction for interacting with multiple databases simultaneously, simplifying the development and maintenance process.
Project-URL: Documentation, https://github.com/amsdal/amsdal-glue?tab=readme-ov-file#amsdal-glue-project
Project-URL: Issues, https://github.com/amsdal/amsdal-glue/issues
Project-URL: Source, https://github.com/amsdal/amsdal-glue/
License:                                  Apache License
License-File: LICENSE.txt
License-File: NOTICE.txt
Classifier: Development Status :: 4 - Beta
Classifier: Programming Language :: Python
Classifier: Programming Language :: Python :: 3.10
Classifier: Programming Language :: Python :: 3.11
Classifier: Programming Language :: Python :: 3.12
Classifier: Programming Language :: Python :: Implementation :: CPython
Classifier: Programming Language :: Python :: Implementation :: PyPy
Requires-Python: >=3.10
